{"cpus": [{"id": 0, "task_groups": {"Cpu0Task0": {"tasks": {"CPU0Task0Subtask6": {"activation": 1, "autostart": false, "priority": 4, "schedule": true, "resources": [], "spinlocks": [], "events": []}, "CPU0Task0Subtask7": {"activation": 1, "autostart": true, "priority": 1, "schedule": true, "resources": [], "spinlocks": [], "events": []}, "CPU0Task0Subtask13": {"activation": 1, "autostart": false, "priority": 3, "schedule": true, "resources": [], "spinlocks": [], "events": []}}, "name": "Cpu0Task0", "promises": {"serialized": true}}, "Cpu0Task2": {"tasks": {"CPU0Task2Subtask3": {"activation": 1, "autostart": true, "priority": 9, "schedule": true, "resources": [], "spinlocks": [], "events": []}, "CPU0Task2Subtask5": {"activation": 1, "autostart": false, "priority": 6, "schedule": true, "resources": [], "spinlocks": [], "events": []}}, "name": "Cpu0Task2", "promises": {"serialized": true}}, "Cpu0Task4": {"tasks": {"CPU0Task4Subtask9": {"activation": 1, "autostart": false, "priority": 13, "schedule": true, "resources": [], "spinlocks": [], "events": []}, "CPU0Task4Subtask11": {"activation": 1, "autostart": true, "priority": 2, "schedule": true, "resources": [], "spinlocks": [], "events": []}}, "name": "Cpu0Task4", "promises": {"serialized": true}}, "Cpu0Task5": {"tasks": {"CPU0Task5Subtask8": {"activation": 1, "autostart": false, "priority": 10, "schedule": true, "resources": [], "spinlocks": [], "events": []}, "CPU0Task5Subtask14": {"activation": 1, "autostart": true, "priority": 7, "schedule": true, "resources": [], "spinlocks": ["LOCK0"], "events": []}}, "name": "Cpu0Task5", "promises": {"serialized": true}}}, "events": {}, "counters": {}, "resources": {}, "alarms": {}}, {"id": 1, "task_groups": {"Cpu1Task1": {"tasks": {"CPU1Task1Subtask1": {"activation": 1, "autostart": true, "priority": 5, "schedule": true, "resources": [], "spinlocks": [], "events": []}, "CPU1Task1Subtask2": {"activation": 1, "autostart": false, "priority": 8, "schedule": true, "resources": [], "spinlocks": ["LOCK0"], "events": []}}, "name": "Cpu1Task1", "promises": {"serialized": true}}, "Cpu1Task3": {"tasks": {"CPU1Task3Subtask0": {"activation": 1, "autostart": true, "priority": 12, "schedule": true, "resources": [], "spinlocks": [], "events": []}, "CPU1Task3Subtask4": {"activation": 1, "autostart": false, "priority": 14, "schedule": true, "resources": [], "spinlocks": [], "events": []}, "CPU1Task3Subtask10": {"activation": 1, "autostart": false, "priority": 11, "schedule": true, "resources": [], "spinlocks": [], "events": []}, "CPU1Task3Subtask12": {"activation": 1, "autostart": false, "priority": 0, "schedule": true, "resources": [], "spinlocks": [], "events": []}}, "name": "Cpu1Task3", "promises": {"serialized": true}}}, "events": {}, "counters": {}, "resources": {}, "alarms": {}}], "spinlocks": [["LOCK0"]]}